pklcache/__init__.py
pklcache-0.3.dist-info/LICENSE
pklcache-0.3.dist-info/METADATA
pklcache-0.3.dist-info/WHEEL
pklcache-0.3.dist-info/top_level.txt
pklcache-0.3.dist-info/RECORD
