Metadata-Version: 2.1
Name: pklcache
Version: 0.3
Summary: Quick and dirty caching of function results on disk using pickle
Home-page: https://github.com/MrSpadala/pklcache
Author: Pietro Spadaccino
License: UNKNOWN
Platform: UNKNOWN
Classifier: Programming Language :: Python :: 3
Classifier: License :: OSI Approved :: MIT License
Classifier: Operating System :: OS Independent
Requires-Python: >=3.5
